{
  "program_id": "github-v0_20645.ll",
  "autophase_features": {
    "BBNumArgsHi": 0,
    "BBNumArgsLo": 14,
    "onePred": 14,
    "onePredOneSuc": 10,
    "onePredTwoSuc": 1,
    "oneSuccessor": 14,
    "twoPred": 14,
    "twoPredOneSuc": 1,
    "twoEach": 13,
    "twoSuccessor": 14,
    "morePreds": 0,
    "BB03Phi": 14,
    "BBHiPhi": 0,
    "BBNoPhi": 17,
    "BeginPhi": 14,
    "BranchCount": 28,
    "returnInt": 0,
    "CriticalCount": 14,
    "NumEdges": 42,
    "const32Bit": 18,
    "const64Bit": 302,
    "numConstZeroes": 155,
    "numConstOnes": 50,
    "UncondBranches": 14,
    "binaryConstArg": 86,
    "NumAShrInst": 0,
    "NumAddInst": 64,
    "NumAllocaInst": 8,
    "NumAndInst": 1,
    "BlockMid": 14,
    "BlockLow": 17,
    "NumBitCastInst": 8,
    "NumBrInst": 28,
    "NumCallInst": 16,
    "NumGetElementPtrInst": 115,
    "NumICmpInst": 17,
    "NumLShrInst": 0,
    "NumLoadInst": 59,
    "NumMulInst": 2,
    "NumOrInst": 36,
    "NumPHIInst": 14,
    "NumRetInst": 3,
    "NumSExtInst": 2,
    "NumSelectInst": 3,
    "NumShlInst": 3,
    "NumStoreInst": 52,
    "NumSubInst": 6,
    "NumTruncInst": 1,
    "NumXorInst": 0,
    "NumZExtInst": 10,
    "TotalBlocks": 31,
    "TotalInsts": 449,
    "TotalMemInst": 250,
    "TotalFuncs": 5,
    "ArgsPhi": 28,
    "testUnary": 88
  },
  "baseline_oz_instcount": 442,
  "knowledge_base_entry": [
    "--scalarizer",
    "--early-cse",
    "--loop-reroll",
    "--instcombine",
    "--loop-instsimplify",
    "--bdce",
    "--elim-avail-extern",
    "--mldst-motion",
    "--jump-threading",
    "--dce",
    "--slp-vectorizer",
    "--correlated-propagation",
    "--load-store-vectorizer",
    "--early-cse-memssa",
    "--loop-fusion",
    "--gvn-hoist",
    "--nary-reassociate",
    "--jump-threading",
    "--lower-expect",
    "--reassociate",
    "--instcombine",
    "--adce",
    "--load-store-vectorizer",
    "--bdce",
    "--sroa",
    "--sccp",
    "--dse",
    "--inline",
    "--slp-vectorizer",
    "--reassociate",
    "--sroa",
    "--sccp",
    "--inline",
    "--dce",
    "--inline",
    "--elim-avail-extern",
    "--mldst-motion",
    "--jump-threading",
    "--dce",
    "--slp-vectorizer",
    "--correlated-propagation",
    "--load-store-vectorizer",
    "--slp-vectorizer",
    "--dse",
    "--newgvn",
    "--nary-reassociate",
    "--loop-fusion",
    "--gvn",
    "--inline",
    "--load-store-vectorizer",
    "--early-cse-memssa",
    "--loop-fusion",
    "--gvn-hoist",
    "--nary-reassociate",
    "--jump-threading",
    "--lower-expect",
    "--reassociate",
    "--instcombine",
    "--adce",
    "--load-store-vectorizer",
    "--bdce",
    "--sroa",
    "--licm",
    "--loop-instsimplify",
    "--newgvn",
    "--loop-instsimplify",
    "--inline",
    "--sroa",
    "--gvn-hoist",
    "--adce",
    "--sroa",
    "--dse",
    "--instsimplify",
    "--prune-eh",
    "--elim-avail-extern",
    "--mldst-motion",
    "--gvn-hoist",
    "--newgvn",
    "--lower-constant-intrinsics",
    "--aggressive-instcombine",
    "--instcombine",
    "--gvn",
    "--lower-constant-intrinsics",
    "--mldst-motion",
    "--mem2reg",
    "--dce",
    "--lower-expect",
    "--reassociate",
    "--instcombine",
    "--adce",
    "--load-store-vectorizer",
    "--bdce",
    "--sroa",
    "--sccp",
    "--dse",
    "--inline",
    "--slp-vectorizer",
    "--reassociate",
    "--sroa",
    "--sccp",
    "--inline",
    "--dce",
    "--inline",
    "--elim-avail-extern",
    "--mldst-motion",
    "--jump-threading",
    "--dce",
    "--slp-vectorizer",
    "--correlated-propagation",
    "--load-store-vectorizer",
    "--slp-vectorizer",
    "--dse",
    "--newgvn",
    "--nary-reassociate",
    "--loop-fusion",
    "--gvn",
    "--inline",
    "--load-store-vectorizer",
    "--early-cse-memssa",
    "--loop-fusion",
    "--gvn-hoist",
    "--nary-reassociate",
    "--jump-threading",
    "--lower-expect",
    "--reassociate",
    "--instcombine",
    "--adce",
    "--load-store-vectorizer",
    "--bdce",
    "--sroa",
    "--licm",
    "--loop-instsimplify",
    "--newgvn",
    "--loop-instsimplify",
    "--inline",
    "--sroa",
    "--gvn-hoist",
    "--adce",
    "--sroa",
    "--dse",
    "--instsimplify",
    "--prune-eh",
    "--elim-avail-extern",
    "--mldst-motion",
    "--gvn-hoist",
    "--newgvn",
    "--lower-constant-intrinsics",
    "--dse",
    "--nary-reassociate",
    "--loop-fusion",
    "--gvn",
    "--nary-reassociate",
    "--correlated-propagation",
    "--simplifycfg"
  ],
  "trajectory": [
    {
      "turn": 1,
      "thought": "Based on the program's characteristics and my experience, I'll formulate a strong initial optimization sequence.",
      "action": "GENERATE_SEQUENCE",
      "action_input": {
        "pass_sequence": [
          "--load-store-vectorizer",
          "--argpromotion",
          "--post-inline-ee-instrument",
          "--lower-widenable-condition",
          "--loop-vectorize",
          "--callsite-splitting",
          "--pgo-memop-opt",
          "--loweratomic",
          "--loop-guard-widening",
          "--loop-reroll",
          "--called-value-propagation",
          "--break-crit-edges",
          "--instcombine",
          "--loop-deletion",
          "--scalarizer",
          "--mem2reg",
          "--alignment-from-assumptions"
        ]
      },
      "observation": {
        "status": "BetterThanOz",
        "performance_vs_Oz": "+37.6%",
        "is_crash": false
      }
    }
  ],
  "final_answer": {
    "pass_sequence": [
      "--load-store-vectorizer",
      "--argpromotion",
      "--post-inline-ee-instrument",
      "--lower-widenable-condition",
      "--loop-vectorize",
      "--callsite-splitting",
      "--pgo-memop-opt",
      "--loweratomic",
      "--loop-guard-widening",
      "--loop-reroll",
      "--called-value-propagation",
      "--break-crit-edges",
      "--instcombine",
      "--loop-deletion",
      "--scalarizer",
      "--mem2reg",
      "--alignment-from-assumptions"
    ],
    "performance_vs_Oz": "+37.6%"
  }
}