{
  "program_id": "github-v0_38166.ll",
  "autophase_features": {
    "BBNumArgsHi": 0,
    "BBNumArgsLo": 2,
    "onePred": 95,
    "onePredOneSuc": 53,
    "onePredTwoSuc": 36,
    "oneSuccessor": 79,
    "twoPred": 42,
    "twoPredOneSuc": 16,
    "twoEach": 22,
    "twoSuccessor": 66,
    "morePreds": 8,
    "BB03Phi": 2,
    "BBHiPhi": 0,
    "BBNoPhi": 157,
    "BeginPhi": 2,
    "BranchCount": 145,
    "returnInt": 7,
    "CriticalCount": 38,
    "NumEdges": 211,
    "const32Bit": 345,
    "const64Bit": 33,
    "numConstZeroes": 198,
    "numConstOnes": 84,
    "UncondBranches": 79,
    "binaryConstArg": 46,
    "NumAShrInst": 0,
    "NumAddInst": 11,
    "NumAllocaInst": 41,
    "NumAndInst": 22,
    "BlockMid": 10,
    "BlockLow": 149,
    "NumBitCastInst": 13,
    "NumBrInst": 145,
    "NumCallInst": 60,
    "NumGetElementPtrInst": 118,
    "NumICmpInst": 69,
    "NumLShrInst": 0,
    "NumLoadInst": 225,
    "NumMulInst": 1,
    "NumOrInst": 2,
    "NumPHIInst": 2,
    "NumRetInst": 8,
    "NumSExtInst": 12,
    "NumSelectInst": 2,
    "NumShlInst": 0,
    "NumStoreInst": 79,
    "NumSubInst": 0,
    "NumTruncInst": 0,
    "NumXorInst": 3,
    "NumZExtInst": 3,
    "TotalBlocks": 159,
    "TotalInsts": 829,
    "TotalMemInst": 523,
    "TotalFuncs": 30,
    "ArgsPhi": 4,
    "testUnary": 294
  },
  "baseline_oz_instcount": 825,
  "knowledge_base_entry": [
    "--strip-nondebug",
    "--mergefunc",
    "--globalopt",
    "--inline",
    "--adce",
    "--instsimplify"
  ],
  "trajectory": [
    {
      "turn": 1,
      "thought": "Based on the program's characteristics and my experience, I'll formulate a strong initial optimization sequence.",
      "action": "GENERATE_SEQUENCE",
      "action_input": {
        "pass_sequence": [
          "--tailcallelim",
          "--elim-avail-extern",
          "--gvn-hoist",
          "--strip-nondebug",
          "--memcpyopt",
          "--speculative-execution",
          "--redundant-dbg-inst-elim",
          "--sancov",
          "--loop-data-prefetch",
          "--ipsccp",
          "--loop-versioning",
          "--die",
          "--constmerge",
          "--sroa",
          "--correlated-propagation",
          "--jump-threading",
          "--globaldce"
        ]
      },
      "observation": {
        "status": "BetterThanOz",
        "performance_vs_Oz": "+0.2%",
        "is_crash": false
      }
    }
  ],
  "final_answer": {
    "pass_sequence": [
      "--tailcallelim",
      "--elim-avail-extern",
      "--gvn-hoist",
      "--strip-nondebug",
      "--memcpyopt",
      "--speculative-execution",
      "--redundant-dbg-inst-elim",
      "--sancov",
      "--loop-data-prefetch",
      "--ipsccp",
      "--loop-versioning",
      "--die",
      "--constmerge",
      "--sroa",
      "--correlated-propagation",
      "--jump-threading",
      "--globaldce"
    ],
    "performance_vs_Oz": "+0.2%"
  }
}