{
  "program_id": "tensorflow-v0_194.ll",
  "autophase_features": {
    "BBNumArgsHi": 5,
    "BBNumArgsLo": 10,
    "onePred": 103,
    "onePredOneSuc": 22,
    "onePredTwoSuc": 65,
    "oneSuccessor": 51,
    "twoPred": 42,
    "twoPredOneSuc": 23,
    "twoEach": 12,
    "twoSuccessor": 86,
    "morePreds": 10,
    "BB03Phi": 15,
    "BBHiPhi": 0,
    "BBNoPhi": 154,
    "BeginPhi": 15,
    "BranchCount": 97,
    "returnInt": 0,
    "CriticalCount": 69,
    "NumEdges": 223,
    "const32Bit": 199,
    "const64Bit": 171,
    "numConstZeroes": 202,
    "numConstOnes": 78,
    "UncondBranches": 51,
    "binaryConstArg": 23,
    "NumAShrInst": 0,
    "NumAddInst": 2,
    "NumAllocaInst": 24,
    "NumAndInst": 16,
    "BlockMid": 6,
    "BlockLow": 163,
    "NumBitCastInst": 81,
    "NumBrInst": 97,
    "NumCallInst": 143,
    "NumGetElementPtrInst": 71,
    "NumICmpInst": 52,
    "NumLShrInst": 2,
    "NumLoadInst": 90,
    "NumMulInst": 0,
    "NumOrInst": 2,
    "NumPHIInst": 26,
    "NumRetInst": 13,
    "NumSExtInst": 1,
    "NumSelectInst": 7,
    "NumShlInst": 1,
    "NumStoreInst": 24,
    "NumSubInst": 4,
    "NumTruncInst": 2,
    "NumXorInst": 0,
    "NumZExtInst": 2,
    "TotalBlocks": 169,
    "TotalInsts": 779,
    "TotalMemInst": 392,
    "TotalFuncs": 60,
    "ArgsPhi": 61,
    "testUnary": 229
  },
  "baseline_oz_instcount": 776,
  "knowledge_base_entry": [
    "--lowerinvoke",
    "--simplifycfg",
    "--nary-reassociate",
    "--indvars",
    "--correlated-propagation",
    "--lower-expect",
    "--mergefunc",
    "--elim-avail-extern",
    "--dce",
    "--sccp",
    "--instcombine",
    "--licm",
    "--globalopt",
    "--early-cse",
    "-loop-reduce",
    "--early-cse-memssa",
    "--reassociate",
    "--globalopt",
    "--flattencfg",
    "--globalopt",
    "--inline",
    "--flattencfg",
    "--gvn-hoist",
    "--slp-vectorizer",
    "--dse",
    "--adce",
    "--inline",
    "--flattencfg",
    "--elim-avail-extern",
    "--mem2reg",
    "--early-cse",
    "--loop-rotate",
    "--jump-threading",
    "--nary-reassociate",
    "--indvars",
    "--gvn",
    "--lower-expect"
  ],
  "trajectory": [
    {
      "turn": 1,
      "thought": "Based on the program's characteristics and my experience, I'll formulate a strong initial optimization sequence.",
      "action": "GENERATE_SEQUENCE",
      "action_input": {
        "pass_sequence": [
          "--lowerinvoke",
          "--argpromotion",
          "--loop-unswitch",
          "--mem2reg",
          "--die",
          "--add-discriminators",
          "--sroa",
          "--infer-address-spaces",
          "--globalopt",
          "--inject-tli-mappings",
          "--sink",
          "--alignment-from-assumptions",
          "--loop-interchange",
          "--constprop",
          "--instcombine",
          "--scalarizer"
        ]
      },
      "observation": {
        "status": "BetterThanOz",
        "performance_vs_Oz": "+25.0%",
        "is_crash": false
      }
    }
  ],
  "final_answer": {
    "pass_sequence": [
      "--lowerinvoke",
      "--argpromotion",
      "--loop-unswitch",
      "--mem2reg",
      "--die",
      "--add-discriminators",
      "--sroa",
      "--infer-address-spaces",
      "--globalopt",
      "--inject-tli-mappings",
      "--sink",
      "--alignment-from-assumptions",
      "--loop-interchange",
      "--constprop",
      "--instcombine",
      "--scalarizer"
    ],
    "performance_vs_Oz": "+25.0%"
  }
}